README.md
setup.cfg
setup.py
plugins/__init__.py
plugins/arrcus.py
pyang_arrcus_plugin.egg-info/PKG-INFO
pyang_arrcus_plugin.egg-info/SOURCES.txt
pyang_arrcus_plugin.egg-info/dependency_links.txt
pyang_arrcus_plugin.egg-info/entry_points.txt
pyang_arrcus_plugin.egg-info/requires.txt
pyang_arrcus_plugin.egg-info/top_level.txt