Metadata-Version: 1.1
Name: pyang-arrcus-plugin
Version: 0.2
Summary: A pyang plugin to validate Arrcus native models
Home-page: https://github.com/mjethanandani/pyang-arrcus-plugin
Author: Mahesh Jethanandani
Author-email: mjethanandani@gmail.com
License: New-style BSD
Download-URL: https://github.com/mjethanandani/pyang-arrcus-plugin/archive/0.2.tar.gz
Keywords: yang,validation
Platform: UNKNOWN
